nasa_apod/__init__.py
nasa_apod/apod.py
nasa_apod-1.0.3.dist-info/METADATA
nasa_apod-1.0.3.dist-info/WHEEL
nasa_apod-1.0.3.dist-info/top_level.txt
nasa_apod-1.0.3.dist-info/RECORD
