Metadata-Version: 2.1
Name: nasa_apod
Version: 1.0.3
Summary: Python package for interacting with NASA APO API
Home-page: https://github.com/aaerrolla/nasa_apod
Author: Anjaneyulu Aerrolla
Author-email: aaerrolla@gmail.com
License: MIT
Requires-Dist: requests
